sgchemist/__init__.py
sgchemist/py.typed
sgchemist/orm/__init__.py
sgchemist/orm/annotation.py
sgchemist/orm/constant.py
sgchemist/orm/engine.py
sgchemist/orm/entity.py
sgchemist/orm/error.py
sgchemist/orm/field_info.py
sgchemist/orm/fields.py
sgchemist/orm/query.py
sgchemist/orm/queryop.py
sgchemist/orm/serializer.py
sgchemist/orm/session.py
sgchemist/orm/typing_alias.py
sgchemist/orm/typing_util.py
sgchemist/schema/__init__.py
sgchemist/schema/generate.py
sgchemist/schema/parse.py
sgchemist-0.0.6.dist-info/LICENSE
sgchemist-0.0.6.dist-info/METADATA
sgchemist-0.0.6.dist-info/WHEEL
sgchemist-0.0.6.dist-info/entry_points.txt
sgchemist-0.0.6.dist-info/top_level.txt
sgchemist-0.0.6.dist-info/RECORD
