Metadata-Version: 2.1
Name: sgchemist
Version: 0.0.6
Summary: An ORM for Autodesk Shotgrid
Author-email: Paul-Emile Buteau <paulemilebuteau@gmail.com>
Project-URL: Homepage, https://github.com/PoloB/sgchemist
Project-URL: Issues, https://github.com/PoloB/sgchemist/issues
Keywords: Shotgrid,Shotgun,Slow Production Tracker,ORM
Classifier: Programming Language :: Python :: 3
Classifier: Programming Language :: Python :: 3.7
Classifier: Programming Language :: Python :: 3.8
Classifier: Programming Language :: Python :: 3.9
Classifier: Programming Language :: Python :: 3.10
Classifier: Programming Language :: Python :: 3.11
Classifier: License :: OSI Approved :: MIT License
Classifier: Operating System :: OS Independent
Classifier: Development Status :: 3 - Alpha
Classifier: Intended Audience :: Developers
Requires-Python: >=3.7
License-File: LICENSE
Requires-Dist: shotgun-api3
Requires-Dist: typing-extensions
